{"BD":"Bangladesh (BD/BGD) in Asia","BE":"Belgium (BE/BEL) in Europe","BF":"Burkina Faso (BF/BFA) in Africa","BG":"Bulgaria (BG/BGR) in Europe","BA":"Bosnia and Herzegovina (BA/BIH) in Europe","BB":"Barbados (BB/BRB) in North America","WF":"Wallis and Futuna (WF/WLF) in Australia & Oceania","BL":"Saint Barthelemy (BL/BLM) in North America","BM":"Bermuda (BM/BMU) in North America","BN":"Brunei (BN/BRN) in Asia","BO":"Bolivia (BO/BOL) in South America","BH":"Bahrain (BH/BHR) in Asia","BI":"Burundi (BI/BDI) in Africa","BJ":"Benin (BJ/BEN) in Africa","BT":"Bhutan (BT/BTN) in Asia","JM":"Jamaica (JM/JAM) in North America","BV":"Bouvet Island (BV/BVT) in Antarctica","BW":"Botswana (BW/BWA) in Africa","WS":"Samoa (WS/WSM) in Australia & Oceania","BQ":"Bonaire, Saint Eustatius and Saba (BQ/BES) in North America","BR":"Brazil (BR/BRA) in South America","BS":"Bahamas (BS/BHS) in North America","JE":"Jersey (JE/JEY) in Europe","BY":"Belarus (BY/BLR) in Europe","BZ":"Belize (BZ/BLZ) in North America","RU":"Russia (RU/RUS) in Europe","RW":"Rwanda (RW/RWA) in Africa","RS":"Serbia (RS/SRB) in Europe","TL":"East Timor (TL/TLS) in Australia & Oceania","RE":"Reunion (RE/REU) in Africa","TM":"Turkmenistan (TM/TKM) in Asia","TJ":"Tajikistan (TJ/TJK) in Asia","RO":"Romania (RO/ROU) in Europe","TK":"Tokelau (TK/TKL) in Australia & Oceania","GW":"Guinea-Bissau (GW/GNB) in Africa","GU":"Guam (GU/GUM) in Australia & Oceania","GT":"Guatemala (GT/GTM) in North America","GS":"South Georgia and the South Sandwich Islands (GS/SGS) in Antarctica","GR":"Greece (GR/GRC) in Europe","GQ":"Equatorial Guinea (GQ/GNQ) in Africa","GP":"Guadeloupe (GP/GLP) in North America","JP":"Japan (JP/JPN) in Asia","GY":"Guyana (GY/GUY) in South America","GG":"Guernsey (GG/GGY) in Europe","GF":"French Guiana (GF/GUF) in South America","GE":"Georgia (GE/GEO) in Asia","GD":"Grenada (GD/GRD) in North America","GB":"United Kingdom (GB/GBR) in Europe","GA":"Gabon (GA/GAB) in Africa","SV":"El Salvador (SV/SLV) in North America","GN":"Guinea (GN/GIN) in Africa","GM":"Gambia (GM/GMB) in Africa","GL":"Greenland (GL/GRL) in North America","GI":"Gibraltar (GI/GIB) in Europe","GH":"Ghana (GH/GHA) in Africa","OM":"Oman (OM/OMN) in Asia","TN":"Tunisia (TN/TUN) in Africa","JO":"Jordan (JO/JOR) in Asia","HR":"Croatia (HR/HRV) in Europe","HT":"Haiti (HT/HTI) in North America","HU":"Hungary (HU/HUN) in Europe","HK":"Hong Kong (HK/HKG) in Asia","HN":"Honduras (HN/HND) in North America","HM":"Heard Island and McDonald Islands (HM/HMD) in Antarctica","VE":"Venezuela (VE/VEN) in South America","PR":"Puerto Rico (PR/PRI) in North America","PS":"Palestinian Territory (PS/PSE) in Asia","PW":"Palau (PW/PLW) in Australia & Oceania","PT":"Portugal (PT/PRT) in Europe","SJ":"Svalbard and Jan Mayen (SJ/SJM) in Europe","PY":"Paraguay (PY/PRY) in South America","IQ":"Iraq (IQ/IRQ) in Asia","PA":"Panama (PA/PAN) in North America","PF":"French Polynesia (PF/PYF) in Australia & Oceania","PG":"Papua New Guinea (PG/PNG) in Australia & Oceania","PE":"Peru (PE/PER) in South America","PK":"Pakistan (PK/PAK) in Asia","PH":"Philippines (PH/PHL) in Asia","PN":"Pitcairn (PN/PCN) in Australia & Oceania","PL":"Poland (PL/POL) in Europe","PM":"Saint Pierre and Miquelon (PM/SPM) in North America","ZM":"Zambia (ZM/ZMB) in Africa","EH":"Western Sahara (EH/ESH) in Africa","EE":"Estonia (EE/EST) in Europe","EG":"Egypt (EG/EGY) in Africa","ZA":"South Africa (ZA/ZAF) in Africa","EC":"Ecuador (EC/ECU) in South America","IT":"Italy (IT/ITA) in Europe","VN":"Vietnam (VN/VNM) in Asia","SB":"Solomon Islands (SB/SLB) in Australia & Oceania","ET":"Ethiopia (ET/ETH) in Africa","SO":"Somalia (SO/SOM) in Africa","ZW":"Zimbabwe (ZW/ZWE) in Africa","SA":"Saudi Arabia (SA/SAU) in Asia","ES":"Spain (ES/ESP) in Europe","ER":"Eritrea (ER/ERI) in Africa","ME":"Montenegro (ME/MNE) in Europe","MD":"Moldova (MD/MDA) in Europe","MG":"Madagascar (MG/MDG) in Africa","MF":"Saint Martin (MF/MAF) in North America","MA":"Morocco (MA/MAR) in Africa","MC":"Monaco (MC/MCO) in Europe","UZ":"Uzbekistan (UZ/UZB) in Asia","MM":"Myanmar (MM/MMR) in Asia","ML":"Mali (ML/MLI) in Africa","MO":"Macao (MO/MAC) in Asia","MN":"Mongolia (MN/MNG) in Asia","MH":"Marshall Islands (MH/MHL) in Australia & Oceania","MK":"Macedonia (MK/MKD) in Europe","MU":"Mauritius (MU/MUS) in Africa","MT":"Malta (MT/MLT) in Europe","MW":"Malawi (MW/MWI) in Africa","MV":"Maldives (MV/MDV) in Asia","MQ":"Martinique (MQ/MTQ) in North America","MP":"Northern Mariana Islands (MP/MNP) in Australia & Oceania","MS":"Montserrat (MS/MSR) in North America","MR":"Mauritania (MR/MRT) in Africa","IM":"Isle of Man (IM/IMN) in Europe","UG":"Uganda (UG/UGA) in Africa","TZ":"Tanzania (TZ/TZA) in Africa","MY":"Malaysia (MY/MYS) in Asia","MX":"Mexico (MX/MEX) in North America","IL":"Israel (IL/ISR) in Asia","FR":"France (FR/FRA) in Europe","IO":"British Indian Ocean Territory (IO/IOT) in Asia","SH":"Saint Helena (SH/SHN) in Africa","FI":"Finland (FI/FIN) in Europe","FJ":"Fiji (FJ/FJI) in Australia & Oceania","FK":"Falkland Islands (FK/FLK) in South America","FM":"Micronesia (FM/FSM) in Australia & Oceania","FO":"Faroe Islands (FO/FRO) in Europe","NI":"Nicaragua (NI/NIC) in North America","NL":"Netherlands (NL/NLD) in Europe","NO":"Norway (NO/NOR) in Europe","NA":"Namibia (NA/NAM) in Africa","VU":"Vanuatu (VU/VUT) in Australia & Oceania","NC":"New Caledonia (NC/NCL) in Australia & Oceania","NE":"Niger (NE/NER) in Africa","NF":"Norfolk Island (NF/NFK) in Australia & Oceania","NG":"Nigeria (NG/NGA) in Africa","NZ":"New Zealand (NZ/NZL) in Australia & Oceania","NP":"Nepal (NP/NPL) in Asia","NR":"Nauru (NR/NRU) in Australia & Oceania","NU":"Niue (NU/NIU) in Australia & Oceania","CK":"Cook Islands (CK/COK) in Australia & Oceania","XK":"Kosovo (XK/XKX) in Europe","CI":"Ivory Coast (CI/CIV) in Africa","CH":"Switzerland (CH/CHE) in Europe","CO":"Colombia (CO/COL) in South America","CN":"China (CN/CHN) in Asia","CM":"Cameroon (CM/CMR) in Africa","CL":"Chile (CL/CHL) in South America","CC":"Cocos Islands (CC/CCK) in Asia","CA":"Canada (CA/CAN) in North America","CG":"Republic of the Congo (CG/COG) in Africa","CF":"Central African Republic (CF/CAF) in Africa","CD":"Democratic Republic of the Congo (CD/COD) in Africa","CZ":"Czech Republic (CZ/CZE) in Europe","CY":"Cyprus (CY/CYP) in Europe","CX":"Christmas Island (CX/CXR) in Asia","CR":"Costa Rica (CR/CRI) in North America","CW":"Curacao (CW/CUW) in North America","CV":"Cape Verde (CV/CPV) in Africa","CU":"Cuba (CU/CUB) in North America","SZ":"Swaziland (SZ/SWZ) in Africa","SY":"Syria (SY/SYR) in Asia","SX":"Sint Maarten (SX/SXM) in North America","KG":"Kyrgyzstan (KG/KGZ) in Asia","KE":"Kenya (KE/KEN) in Africa","SS":"South Sudan (SS/SSD) in Africa","SR":"Suriname (SR/SUR) in South America","KI":"Kiribati (KI/KIR) in Australia & Oceania","KH":"Cambodia (KH/KHM) in Asia","KN":"Saint Kitts and Nevis (KN/KNA) in North America","KM":"Comoros (KM/COM) in Africa","ST":"Sao Tome and Principe (ST/STP) in Africa","SK":"Slovakia (SK/SVK) in Europe","KR":"South Korea (KR/KOR) in Asia","SI":"Slovenia (SI/SVN) in Europe","KP":"North Korea (KP/PRK) in Asia","KW":"Kuwait (KW/KWT) in Asia","SN":"Senegal (SN/SEN) in Africa","SM":"San Marino (SM/SMR) in Europe","SL":"Sierra Leone (SL/SLE) in Africa","SC":"Seychelles (SC/SYC) in Africa","KZ":"Kazakhstan (KZ/KAZ) in Asia","KY":"Cayman Islands (KY/CYM) in North America","SG":"Singapore (SG/SGP) in Asia","SE":"Sweden (SE/SWE) in Europe","SD":"Sudan (SD/SDN) in Africa","DO":"Dominican Republic (DO/DOM) in North America","DM":"Dominica (DM/DMA) in North America","DJ":"Djibouti (DJ/DJI) in Africa","DK":"Denmark (DK/DNK) in Europe","VG":"British Virgin Islands (VG/VGB) in North America","DE":"Germany (DE/DEU) in Europe","YE":"Yemen (YE/YEM) in Asia","DZ":"Algeria (DZ/DZA) in Africa","US":"United States (US/USA) in North America","UY":"Uruguay (UY/URY) in South America","YT":"Mayotte (YT/MYT) in Africa","UM":"United States Minor Outlying Islands (UM/UMI) in Australia & Oceania","LB":"Lebanon (LB/LBN) in Asia","LC":"Saint Lucia (LC/LCA) in North America","LA":"Laos (LA/LAO) in Asia","TV":"Tuvalu (TV/TUV) in Australia & Oceania","TW":"Taiwan (TW/TWN) in Asia","TT":"Trinidad and Tobago (TT/TTO) in North America","TR":"Turkey (TR/TUR) in Asia","LK":"Sri Lanka (LK/LKA) in Asia","LI":"Liechtenstein (LI/LIE) in Europe","LV":"Latvia (LV/LVA) in Europe","TO":"Tonga (TO/TON) in Australia & Oceania","LT":"Lithuania (LT/LTU) in Europe","LU":"Luxembourg (LU/LUX) in Europe","LR":"Liberia (LR/LBR) in Africa","LS":"Lesotho (LS/LSO) in Africa","TH":"Thailand (TH/THA) in Asia","TF":"French Southern Territories (TF/ATF) in Antarctica","TG":"Togo (TG/TGO) in Africa","TD":"Chad (TD/TCD) in Africa","TC":"Turks and Caicos Islands (TC/TCA) in North America","LY":"Libya (LY/LBY) in Africa","VA":"Vatican (VA/VAT) in Europe","VC":"Saint Vincent and the Grenadines (VC/VCT) in North America","AE":"United Arab Emirates (AE/ARE) in Asia","AD":"Andorra (AD/AND) in Europe","AG":"Antigua and Barbuda (AG/ATG) in North America","AF":"Afghanistan (AF/AFG) in Asia","AI":"Anguilla (AI/AIA) in North America","VI":"U.S. Virgin Islands (VI/VIR) in North America","IS":"Iceland (IS/ISL) in Europe","IR":"Iran (IR/IRN) in Asia","AM":"Armenia (AM/ARM) in Asia","AL":"Albania (AL/ALB) in Europe","AO":"Angola (AO/AGO) in Africa","AQ":"Antarctica (AQ/ATA) in Antarctica","AS":"American Samoa (AS/ASM) in Australia & Oceania","AR":"Argentina (AR/ARG) in South America","AU":"Australia (AU/AUS) in Australia & Oceania","AT":"Austria (AT/AUT) in Europe","AW":"Aruba (AW/ABW) in North America","IN":"India (IN/IND) in Asia","AX":"Aland Islands (AX/ALA) in Europe","AZ":"Azerbaijan (AZ/AZE) in Asia","IE":"Ireland (IE/IRL) in Europe","ID":"Indonesia (ID/IDN) in Asia","UA":"Ukraine (UA/UKR) in Europe","QA":"Qatar (QA/QAT) in Asia","MZ":"Mozambique (MZ/MOZ) in Africa"}